{
    "version": "5.3.1",
    "description": "A cross-platform context-aware key remapper.",
    "homepage": "https://github.com/houmain/keymapper",
    "license": "GPL-3.0-only",
    "architecture": {
        "64bit": {
            "url": "https://github.com/houmain/keymapper/releases/download/5.3.1/keymapper-5.3.1-Windows-x86_64.zip",
            "hash": "2036d1a0127b169690072066dd21055fd44624439a1ff1538f1b4a2818b565b6"
        }
    },
    "extract_dir": "keymapper-5.3.1-Windows-x86_64",
    "bin": [
        "keymapper.exe",
        "keymapperctl.exe",
        "keymapperd.exe"
    ],
    "checkver": "github",
    "autoupdate": {
        "architecture": {
            "64bit": {
                "url": "https://github.com/houmain/keymapper/releases/download/$version/keymapper-$version-Windows-x86_64.zip"
            }
        },
        "extract_dir": "keymapper-$version-Windows-x86_64"
    }
}
